Shimarin/__init__.py
Shimarin/client/__init__.py
Shimarin/client/config.py
Shimarin/client/events.py
Shimarin/client/networking.py
Shimarin/plugins/__init__.py
Shimarin/plugins/flask_api/__init__.py
Shimarin/plugins/flask_api/server.py
Shimarin/plugins/middleware/__init__.py
Shimarin/plugins/middleware/persistence.py
Shimarin/plugins/middleware/sqlite_middleware.py
Shimarin/server/__init__.py
Shimarin/server/event.py
Shimarin/server/events.py
Shimarin/server/exceptions.py
shimarin-0.3.6.dist-info/METADATA
shimarin-0.3.6.dist-info/WHEEL
shimarin-0.3.6.dist-info/licenses/LICENSE
shimarin-0.3.6.dist-info/RECORD
